{
  "statusCode": 1,
  "statusMessage": "statusSuccess",
  "data": {
    "id": 117,
    "start_date": "2022-03-10 22:30:29",
    "status": 1,
    "title": "ქვიზი: რა იცი ჰიბრიდულ ომზე?",
    "desc": "ჰიბრიდული ომი უკვე დიდიხანია 21-ე საუკუნის მთავარ გამოწვევად მიიჩნევა. ყველაზე კარგად მას რუსეთი იყენებს. ჰიბრიდულ ომს რუსეთი ბევრი მიმართულებით აწარმოებს, მათ შორის ახლა, უკრაინასთან ომის პერიოდშიც. რუსეთი ცდილობს ჰიბრიდული ომით მოახდინოს უკრაინელების დემორალიზება, ატყუებს საკუთარ მოქალაქეებს, როცა ამ გზით ცდილობს ამ ომში გამარჯვებულად წარმოჩნდეს, ასევე, მისი მიზანია: ძირი გამოუთხაროს პროდასავლურ მთავრობებს, დაასუსტოს ნატო....\nშეავსე ეს ქვიზი და გადაამოწმე შენი ცოდნა ჰიბრიდული ომის შესახებ\n",
    "questions_relation": [
      {
        "id": 518,
        "quiz_id": 117,
        "question": "რა არის ჰიბრიდული ომი?",
        "desc": "",
        "answers_relation": [
          {
            "id": 1502,
            "question_id": 518,
            "is_right_answer": 0,
            "answer": "ჰიბრიდული ომი? - ასეთი რამ არასდროს გამიგია",
            "desc": "ჰიბრიდული ომი არსებობს! ჰიბრიდული ომია, როცა სამხედრო მოქმედებებთან ერთად, სხვადასხვა ხერხებით იბრძვი. ასეთებია, მაგალთად: ტერორიზმი, სეპარატიზმი და მათ შორის ყველაზე მძლავრი, საინფორმაციო ომია. "
          },
          {
            "id": 1503,
            "question_id": 518,
            "is_right_answer": 1,
            "answer": "ჰიბრიდული ომია, როდესაც ცდილობ, მოწინააღმდეგე სამხედრო მოქმედებების გარდა, სხვა საშუალებითაც დაასუსტო და გაანადგურო. ",
            "desc": "მართალია! ყველაზე მძლავრი იარაღი ჰიბრიდულ ომში საინფორმაციო ომია"
          },
          {
            "id": 1504,
            "question_id": 518,
            "is_right_answer": 0,
            "answer": "არც ერთი პასუხი არ არის სწორი",
            "desc": "ჰიბრიდული ომია, როცა სამხედრო მოქმედებებთან ერთად, სხვადასხვა ხერხებით იბრძვი. ასეთებია, მაგალთად: ტერორიზმი, სეპარატიზმი და მათ შორის ყველაზე მძლავრი, საინფორმაციო ომია."
          }
        ]
      },
      {
        "id": 519,
        "quiz_id": 117,
        "question": "რა მიზანი შეიძლება ჰქონდეს საინფორმაციო ომს?",
        "desc": "",
        "answers_relation": [
          {
            "id": 1505,
            "question_id": 519,
            "is_right_answer": 0,
            "answer": "სამიზნე ქვეყანაში არეულობის, კონფლიქტების გამოწვევა",
            "desc": ""
          },
          {
            "id": 1506,
            "question_id": 519,
            "is_right_answer": 0,
            "answer": "საზოგადოების განწყობების ჩამოყალიბება იმ მიმართულებით, როგორც შენ გაწყობს",
            "desc": ""
          },
          {
            "id": 1507,
            "question_id": 519,
            "is_right_answer": 0,
            "answer": "სამიზნე ქვეყნის დისკრედიტაცია",
            "desc": ""
          },
          {
            "id": 1508,
            "question_id": 519,
            "is_right_answer": 1,
            "answer": " ყველა პასუხი სწორია",
            "desc": "მართალია! დაქსასულ და დემორალიზებულ საზოგადოებასთან ბრძოლა, მოწინააღმდეგისთვის უფრო მარტივია"
          }
        ]
      },
      {
        "id": 520,
        "quiz_id": 117,
        "question": "ძირითიდად, როგორი ქვეყნებია საინფორმაციო ომის სამიზნე?",
        "desc": "",
        "answers_relation": [
          {
            "id": 1509,
            "question_id": 520,
            "is_right_answer": 1,
            "answer": "ღარიბი და განვითარებადი ქვეყნები",
            "desc": "მართალია, იმიტომ, რომ ასეთ ქვეყნებს არ აქვთ მძლავრი ინსტრუმენტები მასთან საბრძოლველად. \n\n"
          },
          {
            "id": 1510,
            "question_id": 520,
            "is_right_answer": 0,
            "answer": "ლიდერი ქვეყნები",
            "desc": "რა თქმა უნდა, საინფორმაციო ომის სამიზნე ლიდერი ქვეყნებიც არიან. თუმცა, ისინი მსგავს ომთან გამკლავების ბერკეტსაც ფლობენ"
          }
        ]
      },
      {
        "id": 521,
        "quiz_id": 117,
        "question": "უკრაინაში შეჭრისთანავე რუსეთმა გააქტიურა საინფორმაციო ომიც. შენი აზრით, რას  ემსახურება ეს გზავნილები:",
        "desc": "",
        "answers_relation": [
          {
            "id": 1511,
            "question_id": 521,
            "is_right_answer": 1,
            "answer": "რუსეთი ამ გზავნილებით, ომის დაწყების გამართლებას ცდილობს ",
            "desc": "მართალია!"
          },
          {
            "id": 1512,
            "question_id": 521,
            "is_right_answer": 0,
            "answer": "ეს არის იმის აღწერა, რაც ხდებოდა უკრაინაში ომის დაწყებამდეა",
            "desc": "არა, ეს არ არის სიმართლე. ამ გზავნილებს რუსული პროპაგანდისტული მედიები ავრცელებენ!"
          }
        ]
      },
      {
        "id": 522,
        "quiz_id": 117,
        "question": "რას ემსახურება რუსეთის მიერ გავრცელებული დეზინფორმაცია, რომ უკრაინის შეიარაღებული ძალები იარაღს ყრიან და გარბიან?",
        "desc": "",
        "answers_relation": [
          {
            "id": 1513,
            "question_id": 522,
            "is_right_answer": 0,
            "answer": "ამ გზავნილს არანაირი მიზანი არ აქვს",
            "desc": "მსგავსი ინფორმაციის გავრცელება უკრაინელ ხალხს აფიქრებინებდა, რომ მათი ჯარი დამარცხდა, რაც ბუნებრივია მათ დემორალიზებას და დანებებასაც გამოიწვევდა."
          },
          {
            "id": 1514,
            "question_id": 522,
            "is_right_answer": 1,
            "answer": "უკრაინელი ხალხის დემორალიზებას",
            "desc": "მართალია! მსგავსი ინფორმაციის გავრცელება უკრაინელ ხალხს აფიქრებინებდა, რომ მათი ჯარი დამარცხდა, რაც ბუნებრივია მათ დემორალიზებას და დანებებასაც გამოიწვევდა. "
          },
          {
            "id": 1515,
            "question_id": 522,
            "is_right_answer": 0,
            "answer": "არც ერთი პასუხი არ არის სწორი",
            "desc": "მსგავსი ინფორმაციის გავრცელება უკრაინელ ხალხს აფიქრებინებდა, რომ მათი ჯარი დამარცხდა, რაც ბუნებრივია მათ დემორალიზებას და დანებებასაც გამოიწვევდა."
          }
        ]
      }
    ]
  }
}
